{"expireTime":9007200822188172000,"key":"transformer-remark-markdown-ast-18dd073873bd0e400ec241c00cc0912f-gatsby-remark-imagesgatsby-remark-responsive-iframegatsby-remark-prismjsgatsby-remark-copy-linked-filesgatsby-remark-smartypants-","val":{"type":"root","children":[{"type":"html","value":"<br/>","position":{"start":{"line":1,"column":1,"offset":0},"end":{"line":1,"column":6,"offset":5},"indent":[]}},{"type":"paragraph","children":[{"type":"image","title":null,"url":"muscleman.jpg","alt":"muscleman","position":{"start":{"line":3,"column":1,"offset":9},"end":{"line":3,"column":28,"offset":36},"indent":[]}}],"position":{"start":{"line":3,"column":1,"offset":9},"end":{"line":3,"column":28,"offset":36},"indent":[]}},{"type":"paragraph","children":[{"type":"strong","children":[{"type":"emphasis","children":[{"type":"text","value":"How I might have wasted 33 years of stay in spaceship earth!?","position":{"start":{"line":5,"column":4,"offset":43},"end":{"line":5,"column":65,"offset":104},"indent":[]}}],"position":{"start":{"line":5,"column":3,"offset":42},"end":{"line":5,"column":66,"offset":105},"indent":[]}}],"position":{"start":{"line":5,"column":1,"offset":40},"end":{"line":5,"column":68,"offset":107},"indent":[]}},{"type":"text","value":" ","position":{"start":{"line":5,"column":68,"offset":107},"end":{"line":5,"column":69,"offset":108},"indent":[]}}],"position":{"start":{"line":5,"column":1,"offset":40},"end":{"line":5,"column":69,"offset":108},"indent":[]}},{"type":"paragraph","children":[{"type":"emphasis","children":[{"type":"text","value":"After four lectures of ","position":{"start":{"line":7,"column":2,"offset":113},"end":{"line":7,"column":25,"offset":136},"indent":[]}},{"type":"link","title":null,"url":"","children":[{"type":"text","value":"Human Behavior Biology by Dr. Robert Sapolsky and Stanford","position":{"start":{"line":7,"column":26,"offset":137},"end":{"line":7,"column":84,"offset":195},"indent":[]}}],"position":{"start":{"line":7,"column":25,"offset":136},"end":{"line":7,"column":87,"offset":198},"indent":[]}},{"type":"text","value":", two lectures of ","position":{"start":{"line":7,"column":87,"offset":198},"end":{"line":7,"column":105,"offset":216},"indent":[]}},{"type":"link","title":null,"url":"","children":[{"type":"text","value":"Personality Traits","position":{"start":{"line":7,"column":106,"offset":217},"end":{"line":7,"column":124,"offset":235},"indent":[]}}],"position":{"start":{"line":7,"column":105,"offset":216},"end":{"line":7,"column":127,"offset":238},"indent":[]}},{"type":"text","value":" plus a lot of ","position":{"start":{"line":7,"column":127,"offset":238},"end":{"line":7,"column":142,"offset":253},"indent":[]}},{"type":"link","title":null,"url":"","children":[{"type":"text","value":"Dr. Jordan B. Peterson","position":{"start":{"line":7,"column":143,"offset":254},"end":{"line":7,"column":165,"offset":276},"indent":[]}}],"position":{"start":{"line":7,"column":142,"offset":253},"end":{"line":7,"column":168,"offset":279},"indent":[]}},{"type":"text","value":"’s works or talks","position":{"start":{"line":7,"column":168,"offset":279},"end":{"line":7,"column":185,"offset":296},"indent":[]}}],"position":{"start":{"line":7,"column":1,"offset":112},"end":{"line":7,"column":186,"offset":297},"indent":[]}}],"position":{"start":{"line":7,"column":1,"offset":112},"end":{"line":7,"column":186,"offset":297},"indent":[]}}],"position":{"start":{"line":1,"column":1,"offset":0},"end":{"line":7,"column":186,"offset":297}}}}